collect_columns/__init__.py
collect_columns/collect_columns.py
collect_columns-1.0.0.dist-info/LICENSE
collect_columns-1.0.0.dist-info/METADATA
collect_columns-1.0.0.dist-info/WHEEL
collect_columns-1.0.0.dist-info/entry_points.txt
collect_columns-1.0.0.dist-info/top_level.txt
collect_columns-1.0.0.dist-info/RECORD
