Metadata-Version: 2.1
Name: collect-columns
Version: 1.0.0
Summary: Retrieve a column for each in a set of tables, placing them in a single output table.
Home-page: https://github.com/biowdl/collect-columns
Author: Leiden University Medical Center
Author-email: sasc@lumc.nl
License: MIT
Keywords: bioinformatics
Platform: UNKNOWN
Classifier: Programming Language :: Python :: 3 :: Only
Classifier: Programming Language :: Python :: 3
Classifier: Programming Language :: Python :: 3.5
Classifier: Programming Language :: Python :: 3.6
Classifier: Programming Language :: Python :: 3.7
Classifier: Programming Language :: Python :: 3.8
Classifier: Development Status :: 5 - Production/Stable
Classifier: License :: OSI Approved :: MIT License
Requires-Dist: gffutils
